essex/__init__.py
essex/essex.py
essex/essex_complete.py
essex/requirements.in
essex/requirements.txt
essex-2.0.2.dist-info/entry_points.txt
essex-2.0.2.dist-info/LICENSE
essex-2.0.2.dist-info/WHEEL
essex-2.0.2.dist-info/METADATA
essex-2.0.2.dist-info/RECORD
