Metadata-Version: 2.1
Name: essex
Version: 2.0.2
Summary: A command line interface for creating & managing s6 services, using the s6 toolset
Home-page: https://github.com/AndydeCleyre/essex
License: WTFPL
Keywords: skarnet s6 execline supervise supervision
Author: Andy Kluger
Author-email: AndyKluger@gmail.com
Requires-Python: ~=3.6
Requires-Dist: plumbum >=1.6.7
